system_intelligence/__init__.py
system_intelligence/base_info.py
system_intelligence/cpu_info.py
system_intelligence/gpus_info.py
system_intelligence/hdd_info.py
system_intelligence/host_info.py
system_intelligence/network_info.py
system_intelligence/os_info.py
system_intelligence/query.py
system_intelligence/ram_info.py
system_intelligence/software_info.py
system_intelligence/swap_info.py
system_intelligence/system_intelligence_cli.py
system_intelligence/util/__init__.py
system_intelligence/util/process_util.py
system_intelligence/util/rich_util.py
system_intelligence-2.0.2.dist-info/AUTHORS.rst
system_intelligence-2.0.2.dist-info/LICENSE
system_intelligence-2.0.2.dist-info/METADATA
system_intelligence-2.0.2.dist-info/WHEEL
system_intelligence-2.0.2.dist-info/entry_points.txt
system_intelligence-2.0.2.dist-info/top_level.txt
system_intelligence-2.0.2.dist-info/RECORD
