Metadata-Version: 2.1
Name: system-intelligence
Version: 2.0.2
Summary: Query your system for all hardware and software related information.
Home-page: https://github.com/zethson/system_intelligence
Author: Lukas Heumos
Author-email: lukas.heumos@posteo.net
License: Apache2.0
Keywords: system_intelligence
Platform: UNKNOWN
Classifier: Development Status :: 5 - Production/Stable
Classifier: Intended Audience :: Developers
Classifier: License :: OSI Approved :: Apache Software License
Classifier: Natural Language :: English
Classifier: Programming Language :: Python :: 3
Classifier: Programming Language :: Python :: 3.7
Classifier: Programming Language :: Python :: 3.8
Classifier: Programming Language :: Python :: 3.9
Classifier: Operating System :: Microsoft :: Windows :: Windows 10
Classifier: Operating System :: MacOS :: MacOS X
Classifier: Operating System :: POSIX :: Linux
Requires-Dist: click (>=7.1.2)
Requires-Dist: rich (>=9.9.0)
Requires-Dist: pint (==0.16.1)
Requires-Dist: psutil (==5.8.0)
Requires-Dist: py-cpuinfo (==7.0.0)
Requires-Dist: pyudev (==0.22.0)
Requires-Dist: ruamel.yaml (==0.16.12)
Requires-Dist: json2html (==1.3.0)
